[{"model": "admin.logentry", "pk": 268, "fields": {"action_time": "2022-04-16T14:27:42.167Z", "user": 3, "content_type": 10, "object_id": "27", "object_repr": "Order object (27)", "action_flag": 3, "change_message": ""}}, {"model": "admin.logentry", "pk": 269, "fields": {"action_time": "2022-04-16T14:27:42.177Z", "user": 3, "content_type": 10, "object_id": "26", "object_repr": "Order object (26)", "action_flag": 3, "change_message": ""}}, {"model": "admin.logentry", "pk": 270, "fields": {"action_time": "2022-04-16T14:27:42.182Z", "user": 3, "content_type": 10, "object_id": "25", "object_repr": "Order object (25)", "action_flag": 3, "change_message": ""}}, {"model": "admin.logentry", "pk": 271, "fields": {"action_time": "2022-04-16T14:27:42.188Z", "user": 3, "content_type": 10, "object_id": "24", "object_repr": "Order object (24)", "action_flag": 3, "change_message": ""}}, {"model": "admin.logentry", "pk": 272, "fields": {"action_time": "2022-04-16T14:27:42.193Z", "user": 3, "content_type": 10, "object_id": "23", "object_repr": "Order object (23)", "action_flag": 3, "change_message": ""}}, {"model": "admin.logentry", "pk": 273, "fields": {"action_time": "2022-04-16T14:27:42.198Z", "user": 3, "content_type": 10, "object_id": "22", "object_repr": "Order object (22)", "action_flag": 3, "change_message": ""}}, {"model": "admin.logentry", "pk": 274, "fields": {"action_time": "2022-04-16T14:27:42.202Z", "user": 3, "content_type": 10, "object_id": "21", "object_repr": "Order object (21)", "action_flag": 3, "change_message": ""}}, {"model": "admin.logentry", "pk": 275, "fields": {"action_time": "2022-04-16T14:27:42.206Z", "user": 3, "content_type": 10, "object_id": "20", "object_repr": "Order object (20)", "action_flag": 3, "change_message": ""}}, {"model": "admin.logentry", "pk": 276, "fields": {"action_time": "2022-04-16T14:27:42.210Z", "user": 3, "content_type": 10, "object_id": "19", "object_repr": "Order object (19)", "action_flag": 3, "change_message": ""}}, {"model": "admin.logentry", "pk": 277, "fields": {"action_time": "2022-04-16T14:27:42.214Z", "user": 3, "content_type": 10, "object_id": "18", "object_repr": "Order object (18)", "action_flag": 3, "change_message": ""}}, {"model": "admin.logentry", "pk": 278, "fields": {"action_time": "2022-04-16T14:27:42.218Z", "user": 3, "content_type": 10, "object_id": "17", "object_repr": "Order object (17)", "action_flag": 3, "change_message": ""}}, {"model": "admin.logentry", "pk": 279, "fields": {"action_time": "2022-04-16T14:27:42.222Z", "user": 3, "content_type": 10, "object_id": "16", "object_repr": "Order object (16)", "action_flag": 3, "change_message": ""}}, {"model": "admin.logentry", "pk": 280, "fields": {"action_time": "2022-04-16T14:27:42.227Z", "user": 3, "content_type": 10, "object_id": "15", "object_repr": "Order object (15)", "action_flag": 3, "change_message": ""}}, {"model": "admin.logentry", "pk": 281, "fields": {"action_time": "2022-04-16T14:27:42.230Z", "user": 3, "content_type": 10, "object_id": "14", "object_repr": "Order object (14)", "action_flag": 3, "change_message": ""}}, {"model": "admin.logentry", "pk": 282, "fields": {"action_time": "2022-04-16T14:27:42.234Z", "user": 3, "content_type": 10, "object_id": "13", "object_repr": "Order object (13)", "action_flag": 3, "change_message": ""}}, {"model": "admin.logentry", "pk": 283, "fields": {"action_time": "2022-04-16T14:27:42.238Z", "user": 3, "content_type": 10, "object_id": "12", "object_repr": "Order object (12)", "action_flag": 3, "change_message": ""}}, {"model": "admin.logentry", "pk": 284, "fields": {"action_time": "2022-04-16T14:27:42.243Z", "user": 3, "content_type": 10, "object_id": "11", "object_repr": "Order object (11)", "action_flag": 3, "change_message": ""}}, {"model": "admin.logentry", "pk": 285, "fields": {"action_time": "2022-04-16T14:27:42.248Z", "user": 3, "content_type": 10, "object_id": "10", "object_repr": "Order object (10)", "action_flag": 3, "change_message": ""}}, {"model": "admin.logentry", "pk": 286, "fields": {"action_time": "2022-04-16T14:27:42.253Z", "user": 3, "content_type": 10, "object_id": "9", "object_repr": "Order object (9)", "action_flag": 3, "change_message": ""}}, {"model": "admin.logentry", "pk": 287, "fields": {"action_time": "2022-04-16T14:27:42.261Z", "user": 3, "content_type": 10, "object_id": "8", "object_repr": "Order object (8)", "action_flag": 3, "change_message": ""}}, {"model": "admin.logentry", "pk": 288, "fields": {"action_time": "2022-04-16T14:28:45.619Z", "user": 3, "content_type": 10, "object_id": "30", "object_repr": "Order object (30)", "action_flag": 2, "change_message": "[{\"changed\": {\"fields\": [\"Status\"]}}]"}}, {"model": "admin.logentry", "pk": 289, "fields": {"action_time": "2022-04-16T16:45:39.993Z", "user": 3, "content_type": 4, "object_id": "2", "object_repr": "Tanushree", "action_flag": 3, "change_message": ""}}, {"model": "admin.logentry", "pk": 290, "fields": {"action_time": "2022-04-16T16:45:39.997Z", "user": 3, "content_type": 4, "object_id": "1", "object_repr": "tanushree7252@gmail.com", "action_flag": 3, "change_message": ""}}, {"model": "admin.logentry", "pk": 291, "fields": {"action_time": "2022-04-16T16:45:53.472Z", "user": 3, "content_type": 8, "object_id": "30", "object_repr": "Gifts", "action_flag": 3, "change_message": ""}}, {"model": "admin.logentry", "pk": 292, "fields": {"action_time": "2022-04-16T16:45:53.481Z", "user": 3, "content_type": 8, "object_id": "29", "object_repr": "Health & Personal Care", "action_flag": 3, "change_message": ""}}, {"model": "admin.logentry", "pk": 293, "fields": {"action_time": "2022-04-16T16:45:53.485Z", "user": 3, "content_type": 8, "object_id": "28", "object_repr": "Home & Kitchen", "action_flag": 3, "change_message": ""}}, {"model": "admin.logentry", "pk": 294, "fields": {"action_time": "2022-04-16T16:45:53.488Z", "user": 3, "content_type": 8, "object_id": "27", "object_repr": "Books", "action_flag": 3, "change_message": ""}}, {"model": "admin.logentry", "pk": 295, "fields": {"action_time": "2022-04-16T16:45:53.492Z", "user": 3, "content_type": 8, "object_id": "26", "object_repr": "Shoes & Handbags", "action_flag": 3, "change_message": ""}}, {"model": "admin.logentry", "pk": 296, "fields": {"action_time": "2022-04-16T16:45:53.495Z", "user": 3, "content_type": 8, "object_id": "25", "object_repr": "Watches", "action_flag": 3, "change_message": ""}}, {"model": "admin.logentry", "pk": 297, "fields": {"action_time": "2022-04-16T16:45:53.499Z", "user": 3, "content_type": 8, "object_id": "24", "object_repr": "Kids-Clothing", "action_flag": 3, "change_message": ""}}, {"model": "admin.logentry", "pk": 298, "fields": {"action_time": "2022-04-16T16:45:53.502Z", "user": 3, "content_type": 8, "object_id": "23", "object_repr": "Men-Clothing", "action_flag": 3, "change_message": ""}}, {"model": "admin.logentry", "pk": 299, "fields": {"action_time": "2022-04-16T16:45:53.506Z", "user": 3, "content_type": 8, "object_id": "22", "object_repr": "Women-Clothing", "action_flag": 3, "change_message": ""}}, {"model": "admin.logentry", "pk": 300, "fields": {"action_time": "2022-04-16T16:46:01.462Z", "user": 3, "content_type": 9, "object_id": "10", "object_repr": "Customer object (10)", "action_flag": 3, "change_message": ""}}, {"model": "admin.logentry", "pk": 301, "fields": {"action_time": "2022-04-16T16:46:01.472Z", "user": 3, "content_type": 9, "object_id": "9", "object_repr": "Customer object (9)", "action_flag": 3, "change_message": ""}}, {"model": "admin.logentry", "pk": 302, "fields": {"action_time": "2022-04-16T16:46:01.477Z", "user": 3, "content_type": 9, "object_id": "8", "object_repr": "Customer object (8)", "action_flag": 3, "change_message": ""}}, {"model": "admin.logentry", "pk": 303, "fields": {"action_time": "2022-04-16T16:46:01.485Z", "user": 3, "content_type": 9, "object_id": "7", "object_repr": "Customer object (7)", "action_flag": 3, "change_message": ""}}, {"model": "admin.logentry", "pk": 304, "fields": {"action_time": "2022-04-16T16:46:01.505Z", "user": 3, "content_type": 9, "object_id": "6", "object_repr": "Customer object (6)", "action_flag": 3, "change_message": ""}}, {"model": "admin.logentry", "pk": 305, "fields": {"action_time": "2022-04-16T16:46:01.522Z", "user": 3, "content_type": 9, "object_id": "5", "object_repr": "Customer object (5)", "action_flag": 3, "change_message": ""}}, {"model": "admin.logentry", "pk": 306, "fields": {"action_time": "2022-04-16T16:48:20.866Z", "user": 3, "content_type": 8, "object_id": "31", "object_repr": "Electronics", "action_flag": 1, "change_message": "[{\"added\": {}}]"}}, {"model": "admin.logentry", "pk": 307, "fields": {"action_time": "2022-04-16T16:48:49.372Z", "user": 3, "content_type": 8, "object_id": "32", "object_repr": "Home Decore", "action_flag": 1, "change_message": "[{\"added\": {}}]"}}, {"model": "admin.logentry", "pk": 308, "fields": {"action_time": "2022-04-16T16:48:58.962Z", "user": 3, "content_type": 8, "object_id": "33", "object_repr": "Phones", "action_flag": 1, "change_message": "[{\"added\": {}}]"}}, {"model": "admin.logentry", "pk": 309, "fields": {"action_time": "2022-04-16T16:50:06.690Z", "user": 3, "content_type": 7, "object_id": "105", "object_repr": "Products object (105)", "action_flag": 1, "change_message": "[{\"added\": {}}]"}}, {"model": "admin.logentry", "pk": 310, "fields": {"action_time": "2022-04-16T16:53:36.074Z", "user": 3, "content_type": 7, "object_id": "106", "object_repr": "Products object (106)", "action_flag": 1, "change_message": "[{\"added\": {}}]"}}, {"model": "admin.logentry", "pk": 311, "fields": {"action_time": "2022-04-16T16:55:15.253Z", "user": 3, "content_type": 7, "object_id": "107", "object_repr": "Products object (107)", "action_flag": 1, "change_message": "[{\"added\": {}}]"}}, {"model": "admin.logentry", "pk": 312, "fields": {"action_time": "2022-04-16T16:56:41.268Z", "user": 3, "content_type": 7, "object_id": "108", "object_repr": "Products object (108)", "action_flag": 1, "change_message": "[{\"added\": {}}]"}}, {"model": "admin.logentry", "pk": 313, "fields": {"action_time": "2022-04-16T16:58:19.622Z", "user": 3, "content_type": 7, "object_id": "109", "object_repr": "Products object (109)", "action_flag": 1, "change_message": "[{\"added\": {}}]"}}, {"model": "auth.permission", "pk": 1, "fields": {"name": "Can add log entry", "content_type": 1, "codename": "add_logentry"}}, {"model": "auth.permission", "pk": 2, "fields": {"name": "Can change log entry", "content_type": 1, "codename": "change_logentry"}}, {"model": "auth.permission", "pk": 3, "fields": {"name": "Can delete log entry", "content_type": 1, "codename": "delete_logentry"}}, {"model": "auth.permission", "pk": 4, "fields": {"name": "Can view log entry", "content_type": 1, "codename": "view_logentry"}}, {"model": "auth.permission", "pk": 5, "fields": {"name": "Can add permission", "content_type": 2, "codename": "add_permission"}}, {"model": "auth.permission", "pk": 6, "fields": {"name": "Can change permission", "content_type": 2, "codename": "change_permission"}}, {"model": "auth.permission", "pk": 7, "fields": {"name": "Can delete permission", "content_type": 2, "codename": "delete_permission"}}, {"model": "auth.permission", "pk": 8, "fields": {"name": "Can view permission", "content_type": 2, "codename": "view_permission"}}, {"model": "auth.permission", "pk": 9, "fields": {"name": "Can add group", "content_type": 3, "codename": "add_group"}}, {"model": "auth.permission", "pk": 10, "fields": {"name": "Can change group", "content_type": 3, "codename": "change_group"}}, {"model": "auth.permission", "pk": 11, "fields": {"name": "Can delete group", "content_type": 3, "codename": "delete_group"}}, {"model": "auth.permission", "pk": 12, "fields": {"name": "Can view group", "content_type": 3, "codename": "view_group"}}, {"model": "auth.permission", "pk": 13, "fields": {"name": "Can add user", "content_type": 4, "codename": "add_user"}}, {"model": "auth.permission", "pk": 14, "fields": {"name": "Can change user", "content_type": 4, "codename": "change_user"}}, {"model": "auth.permission", "pk": 15, "fields": {"name": "Can delete user", "content_type": 4, "codename": "delete_user"}}, {"model": "auth.permission", "pk": 16, "fields": {"name": "Can view user", "content_type": 4, "codename": "view_user"}}, {"model": "auth.permission", "pk": 17, "fields": {"name": "Can add content type", "content_type": 5, "codename": "add_contenttype"}}, {"model": "auth.permission", "pk": 18, "fields": {"name": "Can change content type", "content_type": 5, "codename": "change_contenttype"}}, {"model": "auth.permission", "pk": 19, "fields": {"name": "Can delete content type", "content_type": 5, "codename": "delete_contenttype"}}, {"model": "auth.permission", "pk": 20, "fields": {"name": "Can view content type", "content_type": 5, "codename": "view_contenttype"}}, {"model": "auth.permission", "pk": 21, "fields": {"name": "Can add session", "content_type": 6, "codename": "add_session"}}, {"model": "auth.permission", "pk": 22, "fields": {"name": "Can change session", "content_type": 6, "codename": "change_session"}}, {"model": "auth.permission", "pk": 23, "fields": {"name": "Can delete session", "content_type": 6, "codename": "delete_session"}}, {"model": "auth.permission", "pk": 24, "fields": {"name": "Can view session", "content_type": 6, "codename": "view_session"}}, {"model": "auth.permission", "pk": 25, "fields": {"name": "Can add products", "content_type": 7, "codename": "add_products"}}, {"model": "auth.permission", "pk": 26, "fields": {"name": "Can change products", "content_type": 7, "codename": "change_products"}}, {"model": "auth.permission", "pk": 27, "fields": {"name": "Can delete products", "content_type": 7, "codename": "delete_products"}}, {"model": "auth.permission", "pk": 28, "fields": {"name": "Can view products", "content_type": 7, "codename": "view_products"}}, {"model": "auth.permission", "pk": 29, "fields": {"name": "Can add category", "content_type": 8, "codename": "add_category"}}, {"model": "auth.permission", "pk": 30, "fields": {"name": "Can change category", "content_type": 8, "codename": "change_category"}}, {"model": "auth.permission", "pk": 31, "fields": {"name": "Can delete category", "content_type": 8, "codename": "delete_category"}}, {"model": "auth.permission", "pk": 32, "fields": {"name": "Can view category", "content_type": 8, "codename": "view_category"}}, {"model": "auth.permission", "pk": 33, "fields": {"name": "Can add customer", "content_type": 9, "codename": "add_customer"}}, {"model": "auth.permission", "pk": 34, "fields": {"name": "Can change customer", "content_type": 9, "codename": "change_customer"}}, {"model": "auth.permission", "pk": 35, "fields": {"name": "Can delete customer", "content_type": 9, "codename": "delete_customer"}}, {"model": "auth.permission", "pk": 36, "fields": {"name": "Can view customer", "content_type": 9, "codename": "view_customer"}}, {"model": "auth.permission", "pk": 37, "fields": {"name": "Can add order", "content_type": 10, "codename": "add_order"}}, {"model": "auth.permission", "pk": 38, "fields": {"name": "Can change order", "content_type": 10, "codename": "change_order"}}, {"model": "auth.permission", "pk": 39, "fields": {"name": "Can delete order", "content_type": 10, "codename": "delete_order"}}, {"model": "auth.permission", "pk": 40, "fields": {"name": "Can view order", "content_type": 10, "codename": "view_order"}}, {"model": "auth.user", "pk": 3, "fields": {"password": "pbkdf2_sha256$216000$evjWrAZCC8lY$xx4yQ1/4POFFd2y0cIAsWtOKu7ZHLT8rdxFhMpZ9lnY=", "last_login": "2022-04-16T16:51:14.299Z", "is_superuser": true, "username": "user", "first_name": "", "last_name": "", "email": "", "is_staff": true, "is_active": true, "date_joined": "2022-04-10T21:20:26.490Z", "groups": [], "user_permissions": []}}, {"model": "contenttypes.contenttype", "pk": 1, "fields": {"app_label": "admin", "model": "logentry"}}, {"model": "contenttypes.contenttype", "pk": 2, "fields": {"app_label": "auth", "model": "permission"}}, {"model": "contenttypes.contenttype", "pk": 3, "fields": {"app_label": "auth", "model": "group"}}, {"model": "contenttypes.contenttype", "pk": 4, "fields": {"app_label": "auth", "model": "user"}}, {"model": "contenttypes.contenttype", "pk": 5, "fields": {"app_label": "contenttypes", "model": "contenttype"}}, {"model": "contenttypes.contenttype", "pk": 6, "fields": {"app_label": "sessions", "model": "session"}}, {"model": "contenttypes.contenttype", "pk": 7, "fields": {"app_label": "store", "model": "products"}}, {"model": "contenttypes.contenttype", "pk": 8, "fields": {"app_label": "store", "model": "category"}}, {"model": "contenttypes.contenttype", "pk": 9, "fields": {"app_label": "store", "model": "customer"}}, {"model": "contenttypes.contenttype", "pk": 10, "fields": {"app_label": "store", "model": "order"}}, {"model": "sessions.session", "pk": "28wop35rlmddj3wxmdbirrd6i4vgta6b", "fields": {"session_data": ".eJxVjEsOgzAMBe_idRXFxCTAsnvOgBw7KbQVSHxWiLu3SGzYvpl5OwjPKzT78YCOt7XvtiXN3aDQQAG3LbJ80ngCffP4moxM4zoP0ZyKuehi2knT93m5t4Oel_5fIyOx80mEsEAXNJaeLIVckfNOSWrPIYskqzVWGimjRWXHyZbWqcDxAxzvOy4:1lhFXd:R7tY3vcu5kPrKU_Fc-JUSs-E-iuw27ByBvIp3-zjBRY", "expire_date": "2021-05-27T17:54:33.436Z"}}, {"model": "sessions.session", "pk": "drp9m64mj06qfabu5oucczimlq57d8uy", "fields": {"session_data": ".eJxVjDsOgzAQBe-ydWSZLLbXlOlzBrQfCCQRSHwqxN0TJBraNzNvA-VpgWrbb1DzunT1OjdT3RtUgHDZhPXTDAewNw-v0ek4LFMv7lDcSWf3HK35Pk73ctDx3P1r0ug1WkJpW6KWrBCMhCGp5GhlxNIw3YUxFx45ZvEazDR7CoFSTrD_ACmkOrE:1nflnb:SSimdMB3Zp_CONPrgA-W9fZG_DBZSxuk2_nkHYRBBGU", "expire_date": "2022-04-30T17:01:27.167Z"}}, {"model": "sessions.session", "pk": "eb2lprwkfvws8yarbo78n1btqc9e1sxb", "fields": {"session_data": "e30:1liFe9:orgNYuwPAc_2ml4JnhberHcAS-l-yg1I6004fuHQICM", "expire_date": "2021-05-30T12:13:25.399Z"}}, {"model": "sessions.session", "pk": "n252efz44hgcnwsze91voshench4d2kv", "fields": {"session_data": "eyJjYXJ0Ijp7fX0:1lwI7f:w7iFbeWyDdYNdXFYrsKK_LX8SpxBCGiA-RzEskUbbVw", "expire_date": "2021-07-08T05:41:55.020Z"}}, {"model": "sessions.session", "pk": "net3cc7sx2fty20fvtzvp4f9abj002op", "fields": {"session_data": "eyJjYXJ0Ijp7fX0:1lZxo7:4OF1lE9zgLM3Qzpr4gOrOFY19UHizjugPJaakcS6S68", "expire_date": "2021-05-07T15:33:27.605Z"}}, {"model": "sessions.session", "pk": "uaug8ozrov6937ltnl54w80u3lwh4es8", "fields": {"session_data": "eyJjYXJ0Ijp7fX0:1lwHCN:0k6N6a22W_Rbw-Rc2lZE_cDrQXOhvOlh_wAQvfISmjA", "expire_date": "2021-07-08T04:42:43.542Z"}}, {"model": "sessions.session", "pk": "ye5k59xkzi3f35al6qr44r40it3cx3ih", "fields": {"session_data": ".eJxVjDsOgzAQBe-ydWThxXa0lOlzBrQfE0gikDBUiLsnSDS0b2beBsrzAs2236DldenbteS5HQwa8HDZhPWTxwPYm8fX5HQal3kQdyjupMU9J8vfx-leDnou_b8OIcYKE1mdTKMQBtKUUS2QoGXMlbH5DpVilbxZ6u6RkJki1yImsP8AIvU7qg:1lZxcL:fsiGT0hBUFpcQVf7BXR3d0vpEFxEIdz_Wh5XBdL33N8", "expire_date": "2021-05-07T15:21:17.513Z"}}, {"model": "store.category", "pk": 31, "fields": {"name": "Electronics"}}, {"model": "store.category", "pk": 32, "fields": {"name": "Home Decore"}}, {"model": "store.category", "pk": 33, "fields": {"name": "Phones"}}, {"model": "store.products", "pk": 105, "fields": {"name": "Hp Mouse", "price": 600, "category": 31, "description": null, "image": "uploads/products/hpmouse.jpeg"}}, {"model": "store.products", "pk": 106, "fields": {"name": "Realme 7pro", "price": 21000, "category": 33, "description": null, "image": "uploads/products/realme7pro.jpeg"}}, {"model": "store.products", "pk": 107, "fields": {"name": "lamp", "price": 300, "category": 32, "description": null, "image": "uploads/products/lamp1.jpeg"}}, {"model": "store.products", "pk": 108, "fields": {"name": "Realme 6", "price": 18000, "category": 33, "description": null, "image": "uploads/products/realme6.jpeg"}}, {"model": "store.products", "pk": 109, "fields": {"name": "Hp Keyboard", "price": 500, "category": 31, "description": null, "image": "uploads/products/hp_keyboard.jpeg"}}]